libbripy.abi3.so
bripy/__init__.py
.libslibbripy/liblzma-c59ffe58.so.0.0.0
.libslibbripy/libssl-a65b360f.so.0.9.8e
.libslibbripy/libidn-b9d21c09.so.11.5.19
.libslibbripy/libkeyutils-1-ff31573b.2.so
.libslibbripy/libgssapi_krb5-174f8956.so.2.2
.libslibbripy/libcrypto-de69073a.so.0.9.8e
.libslibbripy/libbz2-7225278b.so.1.0.3
.libslibbripy/libselinux-cf8f9094.so.1
.libslibbripy/libsepol-b4f5b513.so.1
.libslibbripy/libkrb5-fb0d2caa.so.3.3
.libslibbripy/libkrb5support-d7ce89d4.so.0.1
.libslibbripy/libk5crypto-622ef25b.so.3.1
.libslibbripy/libcom_err-beb60336.so.2.1
.libslibbripy/libcurl-ff889bed.so.3.0.0
.libslibbripy/libz-a147dcb0.so.1.2.3
bripy-0.0.1a2.dist-info/entry_points.txt
bripy-0.0.1a2.dist-info/RECORD
bripy-0.0.1a2.dist-info/WHEEL
bripy-0.0.1a2.dist-info/top_level.txt
bripy-0.0.1a2.dist-info/METADATA
