Metadata-Version: 2.1
Name: bripy
Version: 0.0.1a2
Summary: Bam read index in python.
Home-page: https://github.com/nanoporetech/bripy
Author: ont-research
License: UNKNOWN
Platform: UNKNOWN
Requires-Python: >=3.5.*,<3.7
Requires-Dist: cffi
